<annotation verified="yes">
	<folder>JPEImages</folder>
	<filename>01856.jpg</filename>
	<path>/home/mimt/ALICE/yolov4-pytorch-master/experiment1/JPEImages/001.jpg</path>
	<source>
		<database>Unknown</database>
	</source>
	<size>
		<width>640</width>
		<height>480</height>
		<depth>3</depth>
	</size>
	<segmented>0</segmented>
<object>
		<name>dfu</name>
		<pose>Unspecified</pose>
		<truncated>0</truncated>
		<difficult>0</difficult>
		<bndbox>
			<xmin>304</xmin>
			<ymin>187</ymin>
			<xmax>396</xmax>
			<ymax>290</ymax>
		</bndbox>
	</object>
<object>
		<name>dfu</name>
		<pose>Unspecified</pose>
		<truncated>0</truncated>
		<difficult>0</difficult>
		<bndbox>
			<xmin>408</xmin>
			<ymin>201</ymin>
			<xmax>448</xmax>
			<ymax>232</ymax>
		</bndbox>
	</object>
</annotation>